flater/library/realtaiizor/net60-windows7/ReaLTaiizor.dll
flater/library/realtaiizor/net60-windows7/ReaLTaiizor.xml
flater/library/realtaiizor.py
flater/test.realtaiizor.1.py
flater/winforms/realtaiizor/__init__.py
flater_realtaiizor-0.1.2.dist-info/METADATA
flater_realtaiizor-0.1.2.dist-info/WHEEL
flater_realtaiizor-0.1.2.dist-info/RECORD
